csgen/__init__.py
csgen/_version.py
csgen/cs_access_modifiers.py
csgen/cs_code_generator.py
csgen-0.1.0.dist-info/WHEEL
csgen-0.1.0.dist-info/LICENSE
csgen-0.1.0.dist-info/METADATA
csgen-0.1.0.dist-info/RECORD
