Metadata-Version: 2.1
Name: csgen
Version: 0.1.0
Summary: Framework for writing generated C# code
Author: ionite34
Author-email: dev@ionite.io
Requires-Python: >=3.10,<3.13
Classifier: Programming Language :: Python :: 3
Classifier: Programming Language :: Python :: 3.10
Classifier: Programming Language :: Python :: 3.11
